{
  "db_name": "PostgreSQL",
  "query": "\n                UPDATE notification_cool_off_tracker\n                SET last_triggered_at = now()\n                WHERE event_type = 'price_changed'\n                AND (last_triggered_at < $1 OR last_triggered_at IS NULL)\n                RETURNING event_type, last_triggered_at\n            ",
  "describe": {
    "columns": [
      {
        "ordinal": 0,
        "name": "event_type",
        "type_info": "Varchar"
      },
      {
        "ordinal": 1,
        "name": "last_triggered_at",
        "type_info": "Timestamptz"
      }
    ],
    "parameters": {
      "Left": [
        "Timestamptz"
      ]
    },
    "nullable": [
      false,
      true
    ]
  },
  "hash": "6f4a7853d8eb1cbb0755273d02cdfacab94becb12aee0f22f11efeb9f763a65e"
}
